{
  "manifestVersion": "3.2",
  "admin": {
    "address": "0x2a45f575451EE21B9C343895697D77cc1fDb6fCc",
    "txHash": "0xac26f41126027834d1fa98a960c2eb869b76ac432d5b70e3609bfae9d67d3f1a"
  },
  "proxies": [
    {
      "address": "0xA3213f4B06292c5b1D47fBaEBa7051727b8567Bd",
      "txHash": "0x05957b53c3cfb6a6c6117cb7bfef80ee59d318b660a19d3ff7c31576f99c921b",
      "kind": "transparent"
    }
  ],
  "impls": {
    "82a0a9b83f2f3ff2119918250c919eb52a39e280abd021a09d1cb816d5960819": {
      "address": "0xaeB705052F7F48Cf333841814C303F7108B83d38",
      "txHash": "0x658d662c3bf18326a18e317cee6c190b34462ef872500cea7d9523d7d0c12f25",
      "layout": {
        "storage": [
          {
            "contract": "Initializable",
            "label": "_initialized",
            "type": "t_bool",
            "src": "../@openzeppelin/contracts-upgradeable/proxy/utils/Initializable.sol:39"
          },
          {
            "contract": "Initializable",
            "label": "_initializing",
            "type": "t_bool",
            "src": "../@openzeppelin/contracts-upgradeable/proxy/utils/Initializable.sol:44"
          },
          {
            "contract": "ContextUpgradeable",
            "label": "__gap",
            "type": "t_array(t_uint256)50_storage",
            "src": "../@openzeppelin/contracts-upgradeable/utils/ContextUpgradeable.sol:36"
          },
          {
            "contract": "ERC20Upgradeable",
            "label": "_balances",
            "type": "t_mapping(t_address,t_uint256)",
            "src": "../@openzeppelin/contracts-upgradeable/token/ERC20/ERC20Upgradeable.sol:37"
          },
          {
            "contract": "ERC20Upgradeable",
            "label": "_allowances",
            "type": "t_mapping(t_address,t_mapping(t_address,t_uint256))",
            "src": "../@openzeppelin/contracts-upgradeable/token/ERC20/ERC20Upgradeable.sol:39"
          },
          {
            "contract": "ERC20Upgradeable",
            "label": "_totalSupply",
            "type": "t_uint256",
            "src": "../@openzeppelin/contracts-upgradeable/token/ERC20/ERC20Upgradeable.sol:41"
          },
          {
            "contract": "ERC20Upgradeable",
            "label": "_name",
            "type": "t_string_storage",
            "src": "../@openzeppelin/contracts-upgradeable/token/ERC20/ERC20Upgradeable.sol:43"
          },
          {
            "contract": "ERC20Upgradeable",
            "label": "_symbol",
            "type": "t_string_storage",
            "src": "../@openzeppelin/contracts-upgradeable/token/ERC20/ERC20Upgradeable.sol:44"
          },
          {
            "contract": "ERC20Upgradeable",
            "label": "__gap",
            "type": "t_array(t_uint256)45_storage",
            "src": "../@openzeppelin/contracts-upgradeable/token/ERC20/ERC20Upgradeable.sol:394"
          }
        ],
        "types": {
          "t_mapping(t_address,t_uint256)": {
            "label": "mapping(address => uint256)"
          },
          "t_address": {
            "label": "address"
          },
          "t_uint256": {
            "label": "uint256"
          },
          "t_mapping(t_address,t_mapping(t_address,t_uint256))": {
            "label": "mapping(address => mapping(address => uint256))"
          },
          "t_string_storage": {
            "label": "string"
          },
          "t_array(t_uint256)45_storage": {
            "label": "uint256[45]"
          },
          "t_array(t_uint256)50_storage": {
            "label": "uint256[50]"
          },
          "t_bool": {
            "label": "bool"
          }
        }
      }
    }
  }
}
